mikro_napari/__init__.py
mikro_napari/api/schema.py
mikro_napari/api/structures.py
mikro_napari/container/__init__.py
mikro_napari/container/base.py
mikro_napari/controllers/app.py
mikro_napari/controllers/base.py
mikro_napari/controllers/sidebar.py
mikro_napari/global_app.py
mikro_napari/manifest.py
mikro_napari/models/representation.py
mikro_napari/napari.yaml
mikro_napari/plugin.py
mikro_napari/run.py
mikro_napari/utils.py
mikro_napari/widgets/base.py
mikro_napari/widgets/dialogs/__init__.py
mikro_napari/widgets/dialogs/open_image.py
mikro_napari/widgets/main_widget.py
mikro_napari/widgets/sidebar/__init__.py
mikro_napari/widgets/sidebar/sidebar.py
mikro_napari/widgets/table/dataframe.py
mikro_napari/widgets/table/table_widget.py
mikro_napari-0.1.63.dist-info/METADATA
mikro_napari-0.1.63.dist-info/WHEEL
mikro_napari-0.1.63.dist-info/entry_points.txt
mikro_napari-0.1.63.dist-info/RECORD
