Metadata-Version: 2.1
Name: mikro-napari
Version: 0.1.63
Summary: A napari plugin to interact with and provide functionality for a connected arkitekt server
Home-page: https://github.com/jhnnsrs/mikro-napari
License: CC BY-NC 3.0
Author: jhnnsrs
Author-email: jhnnsrs@gmail.com
Requires-Python: >=3.8,<=3.12
Classifier: Framework :: napari
Classifier: License :: Other/Proprietary License
Classifier: Programming Language :: Python :: 3
Classifier: Programming Language :: Python :: 3.8
Classifier: Programming Language :: Python :: 3.9
Classifier: Programming Language :: Python :: 3.10
Classifier: Programming Language :: Python :: 3.11
Requires-Dist: arkitekt[fluss,mikro,reaktion,rekuest,unlok] (>=0.5.58)
Project-URL: Repository, https://github.com/jhnnsrs/mikro-napari
